{
  "data": {
    "article": {},
    "attachments": {},
    "author_id": "1840810905833197568",
    "conversation_id": "1989272609469632926",
    "created_at": "2025-11-14T10:02:03.000Z",
    "edit_controls": {
      "editable_until": "2025-11-14T11:02:03.000Z",
      "edits_remaining": 5,
      "is_edit_eligible": false
    },
    "edit_history_tweet_ids": [
      "1989272609469632926"
    ],
    "entities": {
      "mentions": [
        {
          "end": 13,
          "id": "1355034977570701316",
          "start": 3,
          "username": "JCMarkEvo"
        }
      ]
    },
    "geo": {},
    "id": "1989272609469632926",
    "lang": "zh",
    "note_tweet": {
      "entities": {}
    },
    "possibly_sensitive": false,
    "public_metrics": {
      "bookmark_count": 0,
      "impression_count": 0,
      "like_count": 0,
      "quote_count": 0,
      "reply_count": 0,
      "retweet_count": 0
    },
    "referenced_tweets": [
      {
        "id": "1989088885255921916",
        "type": "retweeted"
      }
    ],
    "reply_settings": "everyone",
    "text": "RT @JCMarkEvo: 今天室友开卡开了个大乌龙\n之前没听说过chase在英国开户要信用分，室友开了直接秒拒，叫我也试试，但实际我注册就什么没要就给下卡了\n后来查了一下信用分，我信用分850，室友600多，就很奇怪，明明都是才到这里两个月怎么就差了200多分\n后来才知道，…"
  },
  "includes": {
    "media": [
      {
        "height": 1263,
        "media_key": "3_1989088881111707648",
        "public_metrics": {},
        "type": "photo",
        "url": "https://pbs.twimg.com/media/G5qpzHlXsAA8FrM.jpg",
        "width": 1179
      }
    ],
    "tweets": [
      {
        "article": {},
        "attachments": {},
        "author_id": "1840810905833197568",
        "conversation_id": "1989272609469632926",
        "created_at": "2025-11-14T10:02:03.000Z",
        "edit_controls": {
          "editable_until": "2025-11-14T11:02:03.000Z",
          "edits_remaining": 5,
          "is_edit_eligible": false
        },
        "edit_history_tweet_ids": [
          "1989272609469632926"
        ],
        "entities": {
          "mentions": [
            {
              "end": 13,
              "id": "1355034977570701316",
              "start": 3,
              "username": "JCMarkEvo"
            }
          ]
        },
        "geo": {},
        "id": "1989272609469632926",
        "lang": "zh",
        "note_tweet": {
          "entities": {}
        },
        "possibly_sensitive": false,
        "public_metrics": {
          "bookmark_count": 0,
          "impression_count": 0,
          "like_count": 0,
          "quote_count": 0,
          "reply_count": 0,
          "retweet_count": 0
        },
        "referenced_tweets": [
          {
            "id": "1989088885255921916",
            "type": "retweeted"
          }
        ],
        "reply_settings": "everyone",
        "text": "RT @JCMarkEvo: 今天室友开卡开了个大乌龙\n之前没听说过chase在英国开户要信用分，室友开了直接秒拒，叫我也试试，但实际我注册就什么没要就给下卡了\n后来查了一下信用分，我信用分850，室友600多，就很奇怪，明明都是才到这里两个月怎么就差了200多分\n后来才知道，…"
      },
      {
        "article": {},
        "attachments": {
          "media_keys": [
            "3_1989088881111707648"
          ]
        },
        "author_id": "1355034977570701316",
        "conversation_id": "1989088885255921916",
        "created_at": "2025-11-13T21:52:00.000Z",
        "edit_controls": {
          "editable_until": "2025-11-13T22:52:00.000Z",
          "edits_remaining": 5,
          "is_edit_eligible": true
        },
        "edit_history_tweet_ids": [
          "1989088885255921916"
        ],
        "entities": {
          "urls": [
            {
              "display_url": "pic.x.com/TYafQVIbCm",
              "end": 166,
              "expanded_url": "https://x.com/JCMarkEvo/status/1989088885255921916/photo/1",
              "media_key": "3_1989088881111707648",
              "start": 143,
              "url": "https://t.co/TYafQVIbCm"
            }
          ]
        },
        "geo": {},
        "id": "1989088885255921916",
        "lang": "zh",
        "note_tweet": {
          "entities": {}
        },
        "possibly_sensitive": false,
        "public_metrics": {
          "bookmark_count": 1,
          "impression_count": 845,
          "like_count": 30,
          "quote_count": 0,
          "reply_count": 1,
          "retweet_count": 0
        },
        "reply_settings": "everyone",
        "text": "今天室友开卡开了个大乌龙\n之前没听说过chase在英国开户要信用分，室友开了直接秒拒，叫我也试试，但实际我注册就什么没要就给下卡了\n后来查了一下信用分，我信用分850，室友600多，就很奇怪，明明都是才到这里两个月怎么就差了200多分\n后来才知道，这活爹分期的学费逾期了，自己没发现🌚 https://t.co/TYafQVIbCm"
      }
    ],
    "users": [
      {
        "created_at": "2024-09-30T17:48:26.000Z",
        "description": "🏳️‍🌈/@xubai22｜14岁/初中｜什么领域都懂一点点/人｜嘉兴/杭州/江浙沪常驻｜Founder @xubaimedia｜舍曲林你他妈要咋滴副作用那么多｜爱说梦话/想交朋友。🫠",
        "entities": {
          "description": {
            "mentions": [
              {
                "end": 13,
                "start": 5,
                "username": "xubai22"
              },
              {
                "end": 64,
                "start": 53,
                "username": "xubaimedia"
              }
            ]
          },
          "url": {
            "urls": [
              {
                "display_url": "bonjour.bio/bai",
                "end": 23,
                "expanded_url": "http://bonjour.bio/bai",
                "start": 0,
                "url": "https://t.co/1oWYOoUgy4"
              }
            ]
          }
        },
        "id": "1840810905833197568",
        "location": "localhost:11451",
        "name": "许白🔜广州👉深圳",
        "pinned_tweet_id": "1978469811253649857",
        "profile_image_url": "https://pbs.twimg.com/profile_images/1970537373479178240/o3VFsWsI_normal.jpg",
        "protected": false,
        "public_metrics": {
          "followers_count": 670,
          "following_count": 542,
          "like_count": 6395,
          "listed_count": 0,
          "media_count": 126,
          "tweet_count": 677
        },
        "url": "https://t.co/1oWYOoUgy4",
        "username": "xubai_01",
        "verified": false
      },
      {
        "created_at": "2021-01-29T06:08:18.000Z",
        "description": "你好哦~你怎么来查房了？\n咳咳，这里是Mark，没什么好介绍的，痛苦上学壬，偶尔会掉落一两张手绘，现居苏格兰🏴󠁧󠁢󠁳󠁣󠁴󠁿",
        "id": "1355034977570701316",
        "location": "Port 443",
        "name": "𝓙.𝓒.𝓜𝓪𝓻𝓴🍀",
        "pinned_tweet_id": "1897213562684367065",
        "profile_image_url": "https://pbs.twimg.com/profile_images/1985485840697462784/8RT-1jDT_normal.jpg",
        "protected": false,
        "public_metrics": {
          "followers_count": 3316,
          "following_count": 944,
          "like_count": 33966,
          "listed_count": 18,
          "media_count": 1201,
          "tweet_count": 4875
        },
        "username": "JCMarkEvo",
        "verified": false
      }
    ]
  }
}