{
  "data": {
    "article": {},
    "attachments": {},
    "author_id": "1840810905833197568",
    "conversation_id": "2003395819303805042",
    "created_at": "2025-12-23T09:22:39.000Z",
    "edit_controls": {
      "editable_until": "2025-12-23T10:22:39.000Z",
      "edits_remaining": 5,
      "is_edit_eligible": true
    },
    "edit_history_tweet_ids": [
      "2003395819303805042"
    ],
    "entities": {
      "urls": [
        {
          "display_url": "x.com/xubai_01/statu…",
          "end": 58,
          "expanded_url": "https://twitter.com/xubai_01/status/2003283855365799985",
          "start": 35,
          "url": "https://t.co/XXeKXzXsQw"
        }
      ]
    },
    "geo": {},
    "id": "2003395819303805042",
    "lang": "zh",
    "note_tweet": {
      "entities": {}
    },
    "possibly_sensitive": false,
    "public_metrics": {
      "bookmark_count": 0,
      "impression_count": 0,
      "like_count": 0,
      "quote_count": 0,
      "reply_count": 0,
      "retweet_count": 0
    },
    "referenced_tweets": [
      {
        "id": "2003283855365799985",
        "type": "quoted"
      }
    ],
    "reply_settings": "everyone",
    "text": "原来你他妈是蹭流量的臭双啊🫢你喜欢女生还要说自己是纯给伤人感情。。？ https://t.co/XXeKXzXsQw"
  },
  "includes": {
    "tweets": [
      {
        "article": {},
        "attachments": {},
        "author_id": "1840810905833197568",
        "conversation_id": "2003395819303805042",
        "created_at": "2025-12-23T09:22:39.000Z",
        "edit_controls": {
          "editable_until": "2025-12-23T10:22:39.000Z",
          "edits_remaining": 5,
          "is_edit_eligible": true
        },
        "edit_history_tweet_ids": [
          "2003395819303805042"
        ],
        "entities": {
          "urls": [
            {
              "display_url": "x.com/xubai_01/statu…",
              "end": 58,
              "expanded_url": "https://twitter.com/xubai_01/status/2003283855365799985",
              "start": 35,
              "url": "https://t.co/XXeKXzXsQw"
            }
          ]
        },
        "geo": {},
        "id": "2003395819303805042",
        "lang": "zh",
        "note_tweet": {
          "entities": {}
        },
        "possibly_sensitive": false,
        "public_metrics": {
          "bookmark_count": 0,
          "impression_count": 0,
          "like_count": 0,
          "quote_count": 0,
          "reply_count": 0,
          "retweet_count": 0
        },
        "referenced_tweets": [
          {
            "id": "2003283855365799985",
            "type": "quoted"
          }
        ],
        "reply_settings": "everyone",
        "text": "原来你他妈是蹭流量的臭双啊🫢你喜欢女生还要说自己是纯给伤人感情。。？ https://t.co/XXeKXzXsQw"
      },
      {
        "article": {},
        "attachments": {},
        "author_id": "1840810905833197568",
        "conversation_id": "2003283855365799985",
        "created_at": "2025-12-23T01:57:44.000Z",
        "edit_controls": {
          "editable_until": "2025-12-23T02:57:44.000Z",
          "edits_remaining": 5,
          "is_edit_eligible": true
        },
        "edit_history_tweet_ids": [
          "2003283855365799985"
        ],
        "entities": {},
        "geo": {},
        "id": "2003283855365799985",
        "lang": "zh",
        "note_tweet": {
          "entities": {}
        },
        "possibly_sensitive": false,
        "public_metrics": {
          "bookmark_count": 0,
          "impression_count": 191,
          "like_count": 13,
          "quote_count": 1,
          "reply_count": 1,
          "retweet_count": 0
        },
        "reply_settings": "everyone",
        "text": "更正冬麦瓜条事主年龄：事发时间点高一，现在高二，不是初中生，但是他圈钱还有骗人感情倒是挺。。\n\n祝各位遇到更好的人 不要被渣男耽误"
      }
    ],
    "users": [
      {
        "created_at": "2024-09-30T17:48:26.000Z",
        "description": "🏳️‍🌈/@xubai22｜15岁/初中/12.13🎂/OKX神秘亏钱王交易员｜ADHD&中抑重焦｜Founder @xubaimedia/创业还钱中｜爱说梦话/想交朋友。🫠｜全业务｜2601：宁波/武汉/长沙/昆明｜欢迎随时dm我｜啥意思。",
        "entities": {
          "description": {
            "mentions": [
              {
                "end": 13,
                "start": 5,
                "username": "xubai22"
              },
              {
                "end": 69,
                "start": 58,
                "username": "xubaimedia"
              }
            ]
          },
          "url": {
            "urls": [
              {
                "display_url": "bonjour.bio/bai",
                "end": 23,
                "expanded_url": "http://bonjour.bio/bai",
                "start": 0,
                "url": "https://t.co/1oWYOoUgy4"
              }
            ]
          }
        },
        "id": "1840810905833197568",
        "location": "localhost:11451",
        "name": "许白🔜嘉兴/杭州",
        "pinned_tweet_id": "1991990876240031916",
        "profile_image_url": "https://pbs.twimg.com/profile_images/1970537373479178240/o3VFsWsI_normal.jpg",
        "protected": false,
        "public_metrics": {
          "followers_count": 959,
          "following_count": 768,
          "like_count": 11291,
          "listed_count": 0,
          "media_count": 378,
          "tweet_count": 1690
        },
        "url": "https://t.co/1oWYOoUgy4",
        "username": "xubai_01",
        "verified": false
      }
    ]
  }
}