{
  "data": {
    "article": {},
    "attachments": {},
    "author_id": "1840810905833197568",
    "context_annotations": [
      {
        "domain": {
          "description": "Categories within Brand Verticals that narrow down the scope of Brands",
          "id": "46",
          "name": "Business Taxonomy"
        },
        "entity": {
          "description": "Brands, companies, advertisers and every non-person handle with the profit intent related to Banks, Credit cards, Insurance, Investments, Stocks ",
          "id": "1557696848252391426",
          "name": "Financial Services Business"
        }
      },
      {
        "domain": {
          "description": "Entity Service top level domain, every item that is in Entity Service should be in this domain",
          "id": "30",
          "name": "Entities [Entity Service]"
        },
        "entity": {
          "id": "1139229087682068480",
          "name": "Tether cryptocurrency"
        }
      },
      {
        "domain": {
          "description": "A taxonomy of user interests. ",
          "id": "131",
          "name": "Unified Twitter Taxonomy"
        },
        "entity": {
          "description": "Cryptocurrency",
          "id": "913142676819648512",
          "name": "Cryptocurrencies"
        }
      },
      {
        "domain": {
          "description": "A taxonomy of user interests. ",
          "id": "131",
          "name": "Unified Twitter Taxonomy"
        },
        "entity": {
          "id": "1139229087682068480",
          "name": "Tether cryptocurrency"
        }
      },
      {
        "domain": {
          "description": "A taxonomy of user interests. ",
          "id": "131",
          "name": "Unified Twitter Taxonomy"
        },
        "entity": {
          "id": "1484181943616884743",
          "name": "Cryptocoins"
        }
      },
      {
        "domain": {
          "description": "A taxonomy of user interests. ",
          "id": "131",
          "name": "Unified Twitter Taxonomy"
        },
        "entity": {
          "description": "Cryptocurrency",
          "id": "1492162686204854274",
          "name": "Digital assets & cryptocurrency"
        }
      }
    ],
    "conversation_id": "2069712310743294319",
    "created_at": "2026-06-24T09:20:42.000Z",
    "edit_controls": {
      "editable_until": "2026-06-24T10:20:42.000Z",
      "edits_remaining": 5,
      "is_edit_eligible": true
    },
    "edit_history_tweet_ids": [
      "2069712310743294319"
    ],
    "entities": {
      "urls": [
        {
          "display_url": "x.com/okxchinese/sta…",
          "end": 37,
          "expanded_url": "https://twitter.com/okxchinese/status/2069697040070894046",
          "start": 14,
          "url": "https://t.co/w6ryLsu4In"
        }
      ]
    },
    "geo": {},
    "id": "2069712310743294319",
    "lang": "zh",
    "note_tweet": {
      "entities": {}
    },
    "possibly_sensitive": false,
    "public_metrics": {
      "bookmark_count": 0,
      "impression_count": 0,
      "like_count": 0,
      "quote_count": 0,
      "reply_count": 0,
      "retweet_count": 0
    },
    "referenced_tweets": [
      {
        "id": "2069697040070894046",
        "type": "quoted"
      }
    ],
    "reply_settings": "everyone",
    "text": "看合约地址啊 看名称是？？ https://t.co/w6ryLsu4In"
  },
  "includes": {
    "media": [
      {
        "height": 1620,
        "media_key": "3_2069678310842609664",
        "public_metrics": {},
        "type": "photo",
        "url": "https://pbs.twimg.com/media/HLj5dUUasAAaYSk.jpg",
        "width": 1620
      }
    ],
    "tweets": [
      {
        "article": {},
        "attachments": {},
        "author_id": "1840810905833197568",
        "context_annotations": [
          {
            "domain": {
              "description": "Categories within Brand Verticals that narrow down the scope of Brands",
              "id": "46",
              "name": "Business Taxonomy"
            },
            "entity": {
              "description": "Brands, companies, advertisers and every non-person handle with the profit intent related to Banks, Credit cards, Insurance, Investments, Stocks ",
              "id": "1557696848252391426",
              "name": "Financial Services Business"
            }
          },
          {
            "domain": {
              "description": "Entity Service top level domain, every item that is in Entity Service should be in this domain",
              "id": "30",
              "name": "Entities [Entity Service]"
            },
            "entity": {
              "id": "1139229087682068480",
              "name": "Tether cryptocurrency"
            }
          },
          {
            "domain": {
              "description": "A taxonomy of user interests. ",
              "id": "131",
              "name": "Unified Twitter Taxonomy"
            },
            "entity": {
              "description": "Cryptocurrency",
              "id": "913142676819648512",
              "name": "Cryptocurrencies"
            }
          },
          {
            "domain": {
              "description": "A taxonomy of user interests. ",
              "id": "131",
              "name": "Unified Twitter Taxonomy"
            },
            "entity": {
              "id": "1139229087682068480",
              "name": "Tether cryptocurrency"
            }
          },
          {
            "domain": {
              "description": "A taxonomy of user interests. ",
              "id": "131",
              "name": "Unified Twitter Taxonomy"
            },
            "entity": {
              "id": "1484181943616884743",
              "name": "Cryptocoins"
            }
          },
          {
            "domain": {
              "description": "A taxonomy of user interests. ",
              "id": "131",
              "name": "Unified Twitter Taxonomy"
            },
            "entity": {
              "description": "Cryptocurrency",
              "id": "1492162686204854274",
              "name": "Digital assets & cryptocurrency"
            }
          }
        ],
        "conversation_id": "2069712310743294319",
        "created_at": "2026-06-24T09:20:42.000Z",
        "edit_controls": {
          "editable_until": "2026-06-24T10:20:42.000Z",
          "edits_remaining": 5,
          "is_edit_eligible": true
        },
        "edit_history_tweet_ids": [
          "2069712310743294319"
        ],
        "entities": {
          "urls": [
            {
              "display_url": "x.com/okxchinese/sta…",
              "end": 37,
              "expanded_url": "https://twitter.com/okxchinese/status/2069697040070894046",
              "start": 14,
              "url": "https://t.co/w6ryLsu4In"
            }
          ]
        },
        "geo": {},
        "id": "2069712310743294319",
        "lang": "zh",
        "note_tweet": {
          "entities": {}
        },
        "possibly_sensitive": false,
        "public_metrics": {
          "bookmark_count": 0,
          "impression_count": 0,
          "like_count": 0,
          "quote_count": 0,
          "reply_count": 0,
          "retweet_count": 0
        },
        "referenced_tweets": [
          {
            "id": "2069697040070894046",
            "type": "quoted"
          }
        ],
        "reply_settings": "everyone",
        "text": "看合约地址啊 看名称是？？ https://t.co/w6ryLsu4In"
      },
      {
        "article": {},
        "attachments": {
          "media_keys": [
            "3_2069678310842609664"
          ]
        },
        "author_id": "1461224994705649671",
        "context_annotations": [
          {
            "domain": {
              "description": "Categories within Brand Verticals that narrow down the scope of Brands",
              "id": "46",
              "name": "Business Taxonomy"
            },
            "entity": {
              "description": "Brands, companies, advertisers and every non-person handle with the profit intent related to Banks, Credit cards, Insurance, Investments, Stocks ",
              "id": "1557696848252391426",
              "name": "Financial Services Business"
            }
          },
          {
            "domain": {
              "description": "Entity Service top level domain, every item that is in Entity Service should be in this domain",
              "id": "30",
              "name": "Entities [Entity Service]"
            },
            "entity": {
              "id": "1139229087682068480",
              "name": "Tether cryptocurrency"
            }
          },
          {
            "domain": {
              "description": "A taxonomy of user interests. ",
              "id": "131",
              "name": "Unified Twitter Taxonomy"
            },
            "entity": {
              "description": "Cryptocurrency",
              "id": "913142676819648512",
              "name": "Cryptocurrencies"
            }
          },
          {
            "domain": {
              "description": "A taxonomy of user interests. ",
              "id": "131",
              "name": "Unified Twitter Taxonomy"
            },
            "entity": {
              "id": "1139229087682068480",
              "name": "Tether cryptocurrency"
            }
          },
          {
            "domain": {
              "description": "A taxonomy of user interests. ",
              "id": "131",
              "name": "Unified Twitter Taxonomy"
            },
            "entity": {
              "id": "1484181943616884743",
              "name": "Cryptocoins"
            }
          },
          {
            "domain": {
              "description": "A taxonomy of user interests. ",
              "id": "131",
              "name": "Unified Twitter Taxonomy"
            },
            "entity": {
              "description": "Cryptocurrency",
              "id": "1492162686204854274",
              "name": "Digital assets & cryptocurrency"
            }
          }
        ],
        "conversation_id": "2069697040070894046",
        "created_at": "2026-06-24T08:20:02.000Z",
        "edit_controls": {
          "editable_until": "2026-06-24T09:20:02.000Z",
          "edits_remaining": 5,
          "is_edit_eligible": true
        },
        "edit_history_tweet_ids": [
          "2069697040070894046"
        ],
        "entities": {
          "hashtags": [
            {
              "end": 79,
              "start": 70,
              "tag": "OKX安全小剧场"
            }
          ],
          "urls": [
            {
              "display_url": "pic.x.com/n50DcYWAYL",
              "end": 125,
              "expanded_url": "https://x.com/okxchinese/status/2069697040070894046/photo/1",
              "media_key": "3_2069678310842609664",
              "start": 102,
              "url": "https://t.co/n50DcYWAYL"
            }
          ]
        },
        "geo": {},
        "id": "2069697040070894046",
        "lang": "zh",
        "note_tweet": {
          "entities": {}
        },
        "possibly_sensitive": false,
        "public_metrics": {
          "bookmark_count": 9,
          "impression_count": 10669,
          "like_count": 70,
          "quote_count": 3,
          "reply_count": 132,
          "retweet_count": 25
        },
        "reply_settings": "everyone",
        "text": "🎬以下两个 Token 名称，你能找出区别吗？\n\n· USDT\n· UЅDT\n\n看仔细！一个是你的钱，一个是骗子的饵。评论区留下你的答案， #OKX安全小剧场 为答对的朋友送上30枚正版USDT x5~ https://t.co/n50DcYWAYL"
      }
    ],
    "users": [
      {
        "created_at": "2024-09-30T17:48:26.000Z",
        "description": "HBD🎂Dec/13/2010💛😋\n舞萌痴/Minecraft/排球🏐/羽毛球🏸/🏳️‍🌈泛\n爱说梦话/想交朋友。👀神秘。\n欢迎随时联系/发疯乱叫是常态/全不（栈）开发者\n\n白@xuba1_/鲤鱼@yuji53719/洋洋@xiaoyi969/@xubaimedia/@QWQINC/:)",
        "entities": {
          "description": {
            "mentions": [
              {
                "end": 95,
                "start": 88,
                "username": "xuba1_"
              },
              {
                "end": 108,
                "start": 98,
                "username": "yuji53719"
              },
              {
                "end": 121,
                "start": 111,
                "username": "xiaoyi969"
              },
              {
                "end": 133,
                "start": 122,
                "username": "xubaimedia"
              },
              {
                "end": 141,
                "start": 134,
                "username": "QWQINC"
              }
            ]
          },
          "url": {
            "urls": [
              {
                "display_url": "bonjour.bio/bai",
                "end": 23,
                "expanded_url": "http://bonjour.bio/bai",
                "start": 0,
                "url": "https://t.co/1oWYOoUgy4"
              }
            ]
          }
        },
        "id": "1840810905833197568",
        "location": "ZH,EN / local:11451💚",
        "name": "许白",
        "pinned_tweet_id": "2060623041269522688",
        "profile_image_url": "https://pbs.twimg.com/profile_images/1970537373479178240/o3VFsWsI_normal.jpg",
        "protected": false,
        "public_metrics": {
          "followers_count": 2297,
          "following_count": 1583,
          "like_count": 24818,
          "listed_count": 2,
          "media_count": 1213,
          "tweet_count": 6482
        },
        "url": "https://t.co/1oWYOoUgy4",
        "username": "xubai_01",
        "verified": true
      },
      {
        "created_at": "2021-11-18T06:49:35.000Z",
        "description": "全球领先的加密资产交易平台和Web3平台｜@mancity @mclarenf1 赞助商\n注册领奖励：https://t.co/WUckrWaDMh\nOKX中文社交媒体：https://t.co/LXGDuDmAdk\n*某些产品服务或推广活动不适用于部分地区",
        "entities": {
          "description": {
            "mentions": [
              {
                "end": 29,
                "start": 21,
                "username": "mancity"
              },
              {
                "end": 40,
                "start": 30,
                "username": "mclarenf1"
              }
            ],
            "urls": [
              {
                "display_url": "okx.com/ul/6CngT5?chan…",
                "end": 74,
                "expanded_url": "https://www.okx.com/ul/6CngT5?channelId=TWITTERCN",
                "start": 51,
                "url": "https://t.co/WUckrWaDMh"
              },
              {
                "display_url": "linktr.ee/okxchinese",
                "end": 108,
                "expanded_url": "https://linktr.ee/okxchinese",
                "start": 85,
                "url": "https://t.co/LXGDuDmAdk"
              }
            ]
          },
          "url": {
            "urls": [
              {
                "display_url": "okx.com/ul/6CngT5?chan…",
                "end": 23,
                "expanded_url": "https://www.okx.com/ul/6CngT5?channelId=TWITTERCN",
                "start": 0,
                "url": "https://t.co/WUckrWaDMh"
              }
            ]
          }
        },
        "id": "1461224994705649671",
        "name": "OKX中文",
        "pinned_tweet_id": "2069038045467431307",
        "profile_image_url": "https://pbs.twimg.com/profile_images/2004404711307575296/w6OwQ4Ni_normal.jpg",
        "protected": false,
        "public_metrics": {
          "followers_count": 712388,
          "following_count": 367,
          "like_count": 7554,
          "listed_count": 1743,
          "media_count": 6536,
          "tweet_count": 15493
        },
        "url": "https://t.co/WUckrWaDMh",
        "username": "okxchinese",
        "verified": true
      }
    ]
  }
}