{
  "data": {
    "article": {},
    "attachments": {},
    "author_id": "1840810905833197568",
    "conversation_id": "2045609794237768085",
    "created_at": "2026-04-19T03:00:59.000Z",
    "edit_controls": {
      "editable_until": "2026-04-19T04:00:59.000Z",
      "edits_remaining": 5,
      "is_edit_eligible": false
    },
    "edit_history_tweet_ids": [
      "2045699152890441836"
    ],
    "entities": {
      "mentions": [
        {
          "end": 16,
          "id": "1988906017778962432",
          "start": 0,
          "username": "inrainbows11451"
        }
      ]
    },
    "geo": {},
    "id": "2045699152890441836",
    "in_reply_to_user_id": "1988906017778962432",
    "lang": "zh",
    "note_tweet": {
      "entities": {}
    },
    "possibly_sensitive": false,
    "public_metrics": {
      "bookmark_count": 0,
      "impression_count": 0,
      "like_count": 0,
      "quote_count": 0,
      "reply_count": 0,
      "retweet_count": 0
    },
    "referenced_tweets": [
      {
        "id": "2045693202729251153",
        "type": "replied_to"
      }
    ],
    "reply_settings": "other",
    "text": "@inrainbows11451 哦齁齁齁齁齁帖子要被看光了捏"
  },
  "includes": {
    "tweets": [
      {
        "article": {},
        "attachments": {},
        "author_id": "1840810905833197568",
        "conversation_id": "2045609794237768085",
        "created_at": "2026-04-19T03:00:59.000Z",
        "edit_controls": {
          "editable_until": "2026-04-19T04:00:59.000Z",
          "edits_remaining": 5,
          "is_edit_eligible": false
        },
        "edit_history_tweet_ids": [
          "2045699152890441836"
        ],
        "entities": {
          "mentions": [
            {
              "end": 16,
              "id": "1988906017778962432",
              "start": 0,
              "username": "inrainbows11451"
            }
          ]
        },
        "geo": {},
        "id": "2045699152890441836",
        "in_reply_to_user_id": "1988906017778962432",
        "lang": "zh",
        "note_tweet": {
          "entities": {}
        },
        "possibly_sensitive": false,
        "public_metrics": {
          "bookmark_count": 0,
          "impression_count": 0,
          "like_count": 0,
          "quote_count": 0,
          "reply_count": 0,
          "retweet_count": 0
        },
        "referenced_tweets": [
          {
            "id": "2045693202729251153",
            "type": "replied_to"
          }
        ],
        "reply_settings": "other",
        "text": "@inrainbows11451 哦齁齁齁齁齁帖子要被看光了捏"
      },
      {
        "article": {},
        "attachments": {},
        "author_id": "1988906017778962432",
        "conversation_id": "2045609794237768085",
        "created_at": "2026-04-19T02:37:21.000Z",
        "edit_controls": {
          "editable_until": "2026-04-19T03:37:21.000Z",
          "edits_remaining": 5,
          "is_edit_eligible": false
        },
        "edit_history_tweet_ids": [
          "2045693202729251153"
        ],
        "entities": {
          "mentions": [
            {
              "end": 9,
              "id": "1840810905833197568",
              "start": 0,
              "username": "xubai_01"
            }
          ]
        },
        "geo": {},
        "id": "2045693202729251153",
        "in_reply_to_user_id": "1840810905833197568",
        "lang": "zh",
        "note_tweet": {
          "entities": {}
        },
        "possibly_sensitive": false,
        "public_metrics": {
          "bookmark_count": 0,
          "impression_count": 25,
          "like_count": 1,
          "quote_count": 0,
          "reply_count": 1,
          "retweet_count": 0
        },
        "referenced_tweets": [
          {
            "id": "2045609794237768085",
            "type": "replied_to"
          }
        ],
        "reply_settings": "other",
        "text": "@xubai_01 我将毕生钻研你的推文"
      }
    ],
    "users": [
      {
        "created_at": "2024-09-30T17:48:26.000Z",
        "description": "HBD🎂Dec/13/2010💛😋\n舞萌痴/Minecraft/排球🏐/羽毛球🏸/🏳️‍🌈\n爱说梦话/想交朋友。👀\n欢迎随时联系/发疯乱叫是常态\n\n备@xuba1_/鲤鱼@yuji53719/🐭@mcbd1119/小洋@xiaoyi969/白嘎 @Yazi341384/@xubaimedia/:)",
        "entities": {
          "description": {
            "mentions": [
              {
                "end": 82,
                "start": 75,
                "username": "xuba1_"
              },
              {
                "end": 95,
                "start": 85,
                "username": "yuji53719"
              },
              {
                "end": 106,
                "start": 97,
                "username": "mcbd1119"
              },
              {
                "end": 119,
                "start": 109,
                "username": "xiaoyi969"
              },
              {
                "end": 134,
                "start": 123,
                "username": "Yazi341384"
              },
              {
                "end": 146,
                "start": 135,
                "username": "xubaimedia"
              }
            ]
          },
          "url": {
            "urls": [
              {
                "display_url": "bonjour.bio/bai",
                "end": 23,
                "expanded_url": "http://bonjour.bio/bai",
                "start": 0,
                "url": "https://t.co/1oWYOoUgy4"
              }
            ]
          }
        },
        "id": "1840810905833197568",
        "location": "ZH,EN / local:11451💚 / 🇺🇸LA",
        "name": "许白",
        "pinned_tweet_id": "2009306456848494798",
        "profile_image_url": "https://pbs.twimg.com/profile_images/1970537373479178240/o3VFsWsI_normal.jpg",
        "protected": false,
        "public_metrics": {
          "followers_count": 1692,
          "following_count": 1192,
          "like_count": 20136,
          "listed_count": 0,
          "media_count": 965,
          "tweet_count": 4853
        },
        "url": "https://t.co/1oWYOoUgy4",
        "username": "xubai_01",
        "verified": true
      },
      {
        "created_at": "2025-11-13T09:45:40.000Z",
        "description": "民族自由主义(类Libertarian）/地方主义/L(G)B🏳️‍🌈/文化上有点保守/渴望贴贴喵😭/ dio-swa-nang 潮汕儂",
        "id": "1988906017778962432",
        "name": "In Rainbows 🇹🇼🇨🇳",
        "pinned_tweet_id": "2025825125665563063",
        "profile_image_url": "https://pbs.twimg.com/profile_images/1988906231881428992/BZ0uE1kX_normal.jpg",
        "protected": false,
        "public_metrics": {
          "followers_count": 61,
          "following_count": 127,
          "like_count": 2794,
          "listed_count": 0,
          "media_count": 126,
          "tweet_count": 1368
        },
        "username": "inrainbows11451",
        "verified": false
      }
    ]
  }
}