{
  "data": {
    "article": {},
    "attachments": {},
    "author_id": "1840810905833197568",
    "conversation_id": "2056373365141819507",
    "created_at": "2026-05-18T18:23:33.000Z",
    "edit_controls": {
      "editable_until": "2026-05-18T19:23:33.000Z",
      "edits_remaining": 5,
      "is_edit_eligible": false
    },
    "edit_history_tweet_ids": [
      "2056440570239938715"
    ],
    "entities": {
      "mentions": [
        {
          "end": 11,
          "id": "1753293214826848256",
          "start": 0,
          "username": "tatanakots"
        }
      ]
    },
    "geo": {},
    "id": "2056440570239938715",
    "in_reply_to_user_id": "1753293214826848256",
    "lang": "ja",
    "note_tweet": {
      "entities": {}
    },
    "possibly_sensitive": false,
    "public_metrics": {
      "bookmark_count": 0,
      "impression_count": 0,
      "like_count": 0,
      "quote_count": 0,
      "reply_count": 0,
      "retweet_count": 0
    },
    "referenced_tweets": [
      {
        "id": "2056373365141819507",
        "type": "replied_to"
      }
    ],
    "reply_settings": "everyone",
    "text": "@tatanakots 摸摸"
  },
  "includes": {
    "tweets": [
      {
        "article": {},
        "attachments": {},
        "author_id": "1840810905833197568",
        "conversation_id": "2056373365141819507",
        "created_at": "2026-05-18T18:23:33.000Z",
        "edit_controls": {
          "editable_until": "2026-05-18T19:23:33.000Z",
          "edits_remaining": 5,
          "is_edit_eligible": false
        },
        "edit_history_tweet_ids": [
          "2056440570239938715"
        ],
        "entities": {
          "mentions": [
            {
              "end": 11,
              "id": "1753293214826848256",
              "start": 0,
              "username": "tatanakots"
            }
          ]
        },
        "geo": {},
        "id": "2056440570239938715",
        "in_reply_to_user_id": "1753293214826848256",
        "lang": "ja",
        "note_tweet": {
          "entities": {}
        },
        "possibly_sensitive": false,
        "public_metrics": {
          "bookmark_count": 0,
          "impression_count": 0,
          "like_count": 0,
          "quote_count": 0,
          "reply_count": 0,
          "retweet_count": 0
        },
        "referenced_tweets": [
          {
            "id": "2056373365141819507",
            "type": "replied_to"
          }
        ],
        "reply_settings": "everyone",
        "text": "@tatanakots 摸摸"
      },
      {
        "article": {},
        "attachments": {},
        "author_id": "1753293214826848256",
        "conversation_id": "2056373365141819507",
        "created_at": "2026-05-18T13:56:30.000Z",
        "edit_controls": {
          "editable_until": "2026-05-18T14:56:30.000Z",
          "edits_remaining": 5,
          "is_edit_eligible": true
        },
        "edit_history_tweet_ids": [
          "2056373365141819507"
        ],
        "entities": {},
        "geo": {},
        "id": "2056373365141819507",
        "lang": "zh",
        "note_tweet": {
          "entities": {}
        },
        "possibly_sensitive": false,
        "public_metrics": {
          "bookmark_count": 0,
          "impression_count": 220,
          "like_count": 4,
          "quote_count": 0,
          "reply_count": 2,
          "retweet_count": 0
        },
        "reply_settings": "everyone",
        "text": "今天精神状态可能有点扭曲\n对不起"
      }
    ],
    "users": [
      {
        "created_at": "2024-09-30T17:48:26.000Z",
        "description": "HBD🎂Dec/13/2010💛😋\n舞萌痴/Minecraft/排球🏐/羽毛球🏸/🏳️‍🌈\n爱说梦话/想交朋友。👀｜🏫MKHS\n欢迎随时联系/发疯乱叫是常态\n\n白@xuba1_/鲤鱼@yuji53719/洋洋@xiaoyi969/@xubaimedia/:)",
        "entities": {
          "description": {
            "mentions": [
              {
                "end": 88,
                "start": 81,
                "username": "xuba1_"
              },
              {
                "end": 101,
                "start": 91,
                "username": "yuji53719"
              },
              {
                "end": 114,
                "start": 104,
                "username": "xiaoyi969"
              },
              {
                "end": 126,
                "start": 115,
                "username": "xubaimedia"
              }
            ]
          },
          "url": {
            "urls": [
              {
                "display_url": "bonjour.bio/bai",
                "end": 23,
                "expanded_url": "http://bonjour.bio/bai",
                "start": 0,
                "url": "https://t.co/1oWYOoUgy4"
              }
            ]
          }
        },
        "id": "1840810905833197568",
        "location": "ZH,EN / local:11451💚 / 🇺🇸LA",
        "name": "许白",
        "pinned_tweet_id": "2009306456848494798",
        "profile_image_url": "https://pbs.twimg.com/profile_images/1970537373479178240/o3VFsWsI_normal.jpg",
        "protected": false,
        "public_metrics": {
          "followers_count": 1830,
          "following_count": 1283,
          "like_count": 22388,
          "listed_count": 0,
          "media_count": 1089,
          "tweet_count": 5564
        },
        "url": "https://t.co/1oWYOoUgy4",
        "username": "xubai_01",
        "verified": true
      },
      {
        "created_at": "2024-02-02T05:46:57.000Z",
        "description": "仲良くしましょうよ〜 She/her サブ垢@tatanakots_sub",
        "entities": {
          "description": {
            "mentions": [
              {
                "end": 37,
                "start": 22,
                "username": "tatanakots_sub"
              }
            ]
          },
          "url": {
            "urls": [
              {
                "display_url": "t.mtf.im",
                "end": 23,
                "expanded_url": "http://t.mtf.im",
                "start": 0,
                "url": "https://t.co/p7LtZlX91l"
              }
            ]
          }
        },
        "id": "1753293214826848256",
        "location": "Shanghai, PRC",
        "name": "たたなこ",
        "pinned_tweet_id": "1882824834054504553",
        "profile_image_url": "https://pbs.twimg.com/profile_images/2004564453434724352/E0YeuLGy_normal.jpg",
        "protected": false,
        "public_metrics": {
          "followers_count": 3795,
          "following_count": 418,
          "like_count": 29327,
          "listed_count": 8,
          "media_count": 1736,
          "tweet_count": 12958
        },
        "url": "https://t.co/p7LtZlX91l",
        "username": "tatanakots",
        "verified": false
      }
    ]
  }
}