{
  "data": {
    "article": {},
    "attachments": {},
    "author_id": "1840810905833197568",
    "conversation_id": "2043882820825952314",
    "created_at": "2026-04-14T15:02:05.000Z",
    "edit_controls": {
      "editable_until": "2026-04-14T16:02:05.000Z",
      "edits_remaining": 5,
      "is_edit_eligible": false
    },
    "edit_history_tweet_ids": [
      "2044068681265885652"
    ],
    "entities": {
      "mentions": [
        {
          "end": 12,
          "id": "1681340789757194242",
          "start": 0,
          "username": "bnafo366357"
        }
      ]
    },
    "geo": {},
    "id": "2044068681265885652",
    "in_reply_to_user_id": "1681340789757194242",
    "lang": "en",
    "note_tweet": {
      "entities": {}
    },
    "possibly_sensitive": false,
    "public_metrics": {
      "bookmark_count": 0,
      "impression_count": 0,
      "like_count": 0,
      "quote_count": 0,
      "reply_count": 0,
      "retweet_count": 0
    },
    "referenced_tweets": [
      {
        "id": "2044048041922142533",
        "type": "replied_to"
      }
    ],
    "reply_settings": "other",
    "text": "@bnafo366357 YOUR PHONE LINGING👿"
  },
  "includes": {
    "tweets": [
      {
        "article": {},
        "attachments": {},
        "author_id": "1840810905833197568",
        "conversation_id": "2043882820825952314",
        "created_at": "2026-04-14T15:02:05.000Z",
        "edit_controls": {
          "editable_until": "2026-04-14T16:02:05.000Z",
          "edits_remaining": 5,
          "is_edit_eligible": false
        },
        "edit_history_tweet_ids": [
          "2044068681265885652"
        ],
        "entities": {
          "mentions": [
            {
              "end": 12,
              "id": "1681340789757194242",
              "start": 0,
              "username": "bnafo366357"
            }
          ]
        },
        "geo": {},
        "id": "2044068681265885652",
        "in_reply_to_user_id": "1681340789757194242",
        "lang": "en",
        "note_tweet": {
          "entities": {}
        },
        "possibly_sensitive": false,
        "public_metrics": {
          "bookmark_count": 0,
          "impression_count": 0,
          "like_count": 0,
          "quote_count": 0,
          "reply_count": 0,
          "retweet_count": 0
        },
        "referenced_tweets": [
          {
            "id": "2044048041922142533",
            "type": "replied_to"
          }
        ],
        "reply_settings": "other",
        "text": "@bnafo366357 YOUR PHONE LINGING👿"
      },
      {
        "article": {},
        "attachments": {},
        "author_id": "1681340789757194242",
        "conversation_id": "2043882820825952314",
        "created_at": "2026-04-14T13:40:04.000Z",
        "edit_controls": {
          "editable_until": "2026-04-14T14:40:04.000Z",
          "edits_remaining": 5,
          "is_edit_eligible": false
        },
        "edit_history_tweet_ids": [
          "2044048041922142533"
        ],
        "entities": {
          "mentions": [
            {
              "end": 9,
              "id": "1840810905833197568",
              "start": 0,
              "username": "xubai_01"
            }
          ]
        },
        "geo": {},
        "id": "2044048041922142533",
        "in_reply_to_user_id": "1840810905833197568",
        "lang": "zh",
        "note_tweet": {
          "entities": {}
        },
        "possibly_sensitive": false,
        "public_metrics": {
          "bookmark_count": 0,
          "impression_count": 4,
          "like_count": 1,
          "quote_count": 0,
          "reply_count": 1,
          "retweet_count": 0
        },
        "referenced_tweets": [
          {
            "id": "2043882820825952314",
            "type": "replied_to"
          }
        ],
        "reply_settings": "other",
        "text": "@xubai_01 给我斗笠气掉了（）"
      }
    ],
    "users": [
      {
        "created_at": "2024-09-30T17:48:26.000Z",
        "description": "HBD🎂Dec/13/2010💛😋\n舞萌痴/Minecraft/排球🏐/羽毛球🏸\n爱说梦话/想交朋友。👀\n欢迎随时联系/在这里发疯乱叫是常态\n\n备@xuba1_/鲤鱼@yuji53719/🐭@mcbd1119/小洋@xiaoyi969/@xubaimedia/:)",
        "entities": {
          "description": {
            "mentions": [
              {
                "end": 80,
                "start": 73,
                "username": "xuba1_"
              },
              {
                "end": 93,
                "start": 83,
                "username": "yuji53719"
              },
              {
                "end": 104,
                "start": 95,
                "username": "mcbd1119"
              },
              {
                "end": 117,
                "start": 107,
                "username": "xiaoyi969"
              },
              {
                "end": 129,
                "start": 118,
                "username": "xubaimedia"
              }
            ]
          },
          "url": {
            "urls": [
              {
                "display_url": "bonjour.bio/bai",
                "end": 23,
                "expanded_url": "http://bonjour.bio/bai",
                "start": 0,
                "url": "https://t.co/1oWYOoUgy4"
              }
            ]
          }
        },
        "id": "1840810905833197568",
        "location": "ZH,EN / local:11451💚 / 🇺🇸LA",
        "name": "许白",
        "pinned_tweet_id": "2009306456848494798",
        "profile_image_url": "https://pbs.twimg.com/profile_images/1970537373479178240/o3VFsWsI_normal.jpg",
        "protected": false,
        "public_metrics": {
          "followers_count": 1612,
          "following_count": 1160,
          "like_count": 19192,
          "listed_count": 0,
          "media_count": 923,
          "tweet_count": 4681
        },
        "url": "https://t.co/1oWYOoUgy4",
        "username": "xubai_01",
        "verified": true
      },
      {
        "created_at": "2023-07-18T16:31:10.000Z",
        "description": "【⚠️偶尔的负能量传递注意】【⚠️推止于推⚠️】\n坐标成都 15/175/79kg 男♂性 喜欢男 爱看梗图/男同 半i人半e人\n玩第五人格（不活跃）/雀魂/舞萌/jubeat\n本号是nafo的碎碎念\n（原名：精神病院院长）",
        "id": "1681340789757194242",
        "location": "锦江区第四人民医院",
        "name": "纳福nafo",
        "pinned_tweet_id": "2041512687088382418",
        "profile_image_url": "https://pbs.twimg.com/profile_images/2038273709476392960/Au6xLnZY_normal.jpg",
        "protected": false,
        "public_metrics": {
          "followers_count": 22,
          "following_count": 714,
          "like_count": 6654,
          "listed_count": 0,
          "media_count": 98,
          "tweet_count": 1372
        },
        "username": "bnafo366357",
        "verified": false
      }
    ]
  }
}