{
  "data": {
    "article": {},
    "attachments": {},
    "author_id": "1840810905833197568",
    "conversation_id": "2074297301665993091",
    "created_at": "2026-07-07T07:05:28.000Z",
    "edit_controls": {
      "editable_until": "2026-07-07T08:05:28.000Z",
      "edits_remaining": 5,
      "is_edit_eligible": false
    },
    "edit_history_tweet_ids": [
      "2074389318039392481"
    ],
    "entities": {
      "mentions": [
        {
          "end": 12,
          "id": "2049917770138058752",
          "start": 0,
          "username": "GinpikaPika"
        }
      ]
    },
    "geo": {},
    "id": "2074389318039392481",
    "in_reply_to_user_id": "2049917770138058752",
    "lang": "zh",
    "note_tweet": {
      "entities": {}
    },
    "possibly_sensitive": false,
    "public_metrics": {
      "bookmark_count": 0,
      "impression_count": 0,
      "like_count": 0,
      "quote_count": 0,
      "reply_count": 0,
      "retweet_count": 0
    },
    "referenced_tweets": [
      {
        "id": "2074378570877845801",
        "type": "replied_to"
      }
    ],
    "reply_settings": "everyone",
    "text": "@GinpikaPika 哦齁齁齁齁齁齁"
  },
  "includes": {
    "tweets": [
      {
        "article": {},
        "attachments": {},
        "author_id": "1840810905833197568",
        "conversation_id": "2074297301665993091",
        "created_at": "2026-07-07T07:05:28.000Z",
        "edit_controls": {
          "editable_until": "2026-07-07T08:05:28.000Z",
          "edits_remaining": 5,
          "is_edit_eligible": false
        },
        "edit_history_tweet_ids": [
          "2074389318039392481"
        ],
        "entities": {
          "mentions": [
            {
              "end": 12,
              "id": "2049917770138058752",
              "start": 0,
              "username": "GinpikaPika"
            }
          ]
        },
        "geo": {},
        "id": "2074389318039392481",
        "in_reply_to_user_id": "2049917770138058752",
        "lang": "zh",
        "note_tweet": {
          "entities": {}
        },
        "possibly_sensitive": false,
        "public_metrics": {
          "bookmark_count": 0,
          "impression_count": 0,
          "like_count": 0,
          "quote_count": 0,
          "reply_count": 0,
          "retweet_count": 0
        },
        "referenced_tweets": [
          {
            "id": "2074378570877845801",
            "type": "replied_to"
          }
        ],
        "reply_settings": "everyone",
        "text": "@GinpikaPika 哦齁齁齁齁齁齁"
      },
      {
        "article": {},
        "attachments": {},
        "author_id": "2049917770138058752",
        "conversation_id": "2074297301665993091",
        "created_at": "2026-07-07T06:22:46.000Z",
        "edit_controls": {
          "editable_until": "2026-07-07T07:22:46.000Z",
          "edits_remaining": 5,
          "is_edit_eligible": false
        },
        "edit_history_tweet_ids": [
          "2074378570877845801"
        ],
        "entities": {
          "mentions": [
            {
              "end": 9,
              "id": "1840810905833197568",
              "start": 0,
              "username": "xubai_01"
            }
          ]
        },
        "geo": {},
        "id": "2074378570877845801",
        "in_reply_to_user_id": "1840810905833197568",
        "lang": "ja",
        "note_tweet": {
          "entities": {}
        },
        "possibly_sensitive": false,
        "public_metrics": {
          "bookmark_count": 0,
          "impression_count": 5,
          "like_count": 1,
          "quote_count": 0,
          "reply_count": 1,
          "retweet_count": 0
        },
        "referenced_tweets": [
          {
            "id": "2074297301665993091",
            "type": "replied_to"
          }
        ],
        "reply_settings": "everyone",
        "text": "@xubai_01 一想到蒙德还有粉毛小男孩神父，我就噢齁齁齁齁"
      }
    ],
    "users": [
      {
        "created_at": "2024-09-30T17:48:26.000Z",
        "description": "HBD🎂Dec/13/2010💛😋\n舞萌痴/Minecraft/排球🏐/羽毛球🏸/🏳️‍🌈泛\n爱说梦话/想交朋友。👀神秘。\n欢迎随时联系/发疯乱叫是常态/全不（栈）开发者\n\n白@xuba1_/鲤鱼@yuji53719/@xubaimedia/@QWQINC/:)\n\n🐧3454925306",
        "entities": {
          "description": {
            "mentions": [
              {
                "end": 95,
                "start": 88,
                "username": "xuba1_"
              },
              {
                "end": 108,
                "start": 98,
                "username": "yuji53719"
              },
              {
                "end": 120,
                "start": 109,
                "username": "xubaimedia"
              },
              {
                "end": 128,
                "start": 121,
                "username": "QWQINC"
              }
            ]
          },
          "url": {
            "urls": [
              {
                "display_url": "bonjour.bio/bai",
                "end": 23,
                "expanded_url": "http://bonjour.bio/bai",
                "start": 0,
                "url": "https://t.co/1oWYOoUgy4"
              }
            ]
          }
        },
        "id": "1840810905833197568",
        "location": "ZH,EN / local:11451💚",
        "name": "许白",
        "pinned_tweet_id": "2060623041269522688",
        "profile_image_url": "https://pbs.twimg.com/profile_images/1970537373479178240/o3VFsWsI_normal.jpg",
        "protected": false,
        "public_metrics": {
          "followers_count": 2408,
          "following_count": 1643,
          "like_count": 25631,
          "listed_count": 2,
          "media_count": 1284,
          "tweet_count": 6876
        },
        "url": "https://t.co/1oWYOoUgy4",
        "username": "xubai_01",
        "verified": true
      },
      {
        "created_at": "2026-04-30T18:24:37.000Z",
        "description": "是61岁的男高一枚，性取向为double。喜欢看番，喜欢音乐，喜欢拼胶，喜欢小正太（完全是正太重度依赖来的嗯对）。目前打算把推当朋友圈发，可接hk（仅限与我年龄相仿）\n欢迎大家来跟我聊天呀",
        "id": "2049917770138058752",
        "name": "Baga shinji",
        "profile_image_url": "https://pbs.twimg.com/profile_images/2072562776309182464/NCjOJu_H_normal.jpg",
        "protected": false,
        "public_metrics": {
          "followers_count": 7,
          "following_count": 267,
          "like_count": 1,
          "listed_count": 0,
          "media_count": 5,
          "tweet_count": 67
        },
        "url": "",
        "username": "GinpikaPika",
        "verified": false
      }
    ]
  }
}